gpt_trans/__init__.py
gpt_trans/main.py
gpt_trans/prompt_template/__init__.py
gpt_trans/splitter/__init__.py
gpt_trans/splitter/markdown_splitter.py
gpt_trans-0.0.4.dist-info/METADATA
gpt_trans-0.0.4.dist-info/WHEEL
gpt_trans-0.0.4.dist-info/entry_points.txt
gpt_trans-0.0.4.dist-info/top_level.txt
gpt_trans-0.0.4.dist-info/RECORD
